jx3api/__init__.py
jx3api/exception.py
jx3api/jx3api.py
jx3api-20240417.dist-info/METADATA
jx3api-20240417.dist-info/WHEEL
jx3api-20240417.dist-info/top_level.txt
jx3api-20240417.dist-info/RECORD
